Metadata-Version: 2.1
Name: biopandas
Version: 0.5.1
Summary: Machine Learning Library Extensions
Home-page: https://github.com/rasbt/biopandas
Author: Sebastian Raschka
Author-email: mail@sebastianraschka.com
License: BSD 3-Clause
Platform: any
Classifier: License :: OSI Approved :: BSD License
Classifier: Development Status :: 5 - Production/Stable
Classifier: Operating System :: Microsoft :: Windows
Classifier: Operating System :: POSIX
Classifier: Operating System :: Unix
Classifier: Operating System :: MacOS
Classifier: Programming Language :: Python :: 3
Classifier: Programming Language :: Python :: 3.5
Classifier: Programming Language :: Python :: 3.6
Classifier: Programming Language :: Python :: 3.7
Classifier: Programming Language :: Python :: 3.8
Classifier: Programming Language :: Python :: 3.9
Classifier: Topic :: Scientific/Engineering
License-File: LICENSE.txt
Requires-Dist: numpy>=1.16.2
Requires-Dist: pandas>=0.24.2
Requires-Dist: mmtf-python==1.1.3
Requires-Dist: looseversion==1.1.2
Requires-Dist: setuptools
Provides-Extra: test
Requires-Dist: pytest; extra == "test"
Requires-Dist: pytest-cov; extra == "test"
Requires-Dist: flake8; extra == "test"
